HISTORY.rst
LICENSE
MANIFEST.in
README.rst
setup.py
txwac.py
txwac.egg-info/PKG-INFO
txwac.egg-info/SOURCES.txt
txwac.egg-info/dependency_links.txt
txwac.egg-info/pbr.json
txwac.egg-info/requires.txt
txwac.egg-info/top_level.txt