Metadata-Version: 1.1
Name: txwac
Version: 0.2
Summary: Writing RESTful API clients.
Home-page: https://github.com/trenton42/txwac/
Author: wac
Author-email: wac@example.com
License: Copyright (c) 2012 wac.
